sagemaker_jupyterlab_extension/__init__.py
sagemaker_jupyterlab_extension/_version.py
sagemaker_jupyterlab_extension/handlers.py
sagemaker_jupyterlab_extension/labextension/package.json
sagemaker_jupyterlab_extension/labextension/static/10.e9ece26111f932555500.js
sagemaker_jupyterlab_extension/labextension/static/222.97a7340eb9a96f1ec6f4.js
sagemaker_jupyterlab_extension/labextension/static/326.5aa6f4137e4bba998450.js
sagemaker_jupyterlab_extension/labextension/static/378.d56530ddaee02ebb4cb6.js
sagemaker_jupyterlab_extension/labextension/static/398.ed315cd2dc4697f59947.js
sagemaker_jupyterlab_extension/labextension/static/495.c4a331efcf52b1c1d02f.js
sagemaker_jupyterlab_extension/labextension/static/505.d3d2b55da30b1967a4ee.js
sagemaker_jupyterlab_extension/labextension/static/515.414622cd4472750d064f.js
sagemaker_jupyterlab_extension/labextension/static/515.414622cd4472750d064f.js.LICENSE.txt
sagemaker_jupyterlab_extension/labextension/static/609.01dc90abdcf28dc08e22.js
sagemaker_jupyterlab_extension/labextension/static/609.01dc90abdcf28dc08e22.js.LICENSE.txt
sagemaker_jupyterlab_extension/labextension/static/638.0b12e5718f139afa872f.js
sagemaker_jupyterlab_extension/labextension/static/641.5949212aee55e6992c6e.js
sagemaker_jupyterlab_extension/labextension/static/644.c07f146c90c08361cb66.js
sagemaker_jupyterlab_extension/labextension/static/678.f5100fabedcf73bea3c2.js
sagemaker_jupyterlab_extension/labextension/static/678.f5100fabedcf73bea3c2.js.LICENSE.txt
sagemaker_jupyterlab_extension/labextension/static/700.edf289c93c12d876dcb8.js
sagemaker_jupyterlab_extension/labextension/static/762.6cb48de995607ed5b3a5.js
sagemaker_jupyterlab_extension/labextension/static/762.6cb48de995607ed5b3a5.js.LICENSE.txt
sagemaker_jupyterlab_extension/labextension/static/792.d2ba6dfc0e227b6bf9ef.js
sagemaker_jupyterlab_extension/labextension/static/860.210e65e5b96f9486f864.js
sagemaker_jupyterlab_extension/labextension/static/995.990255c0d9aecc0d7f95.js
sagemaker_jupyterlab_extension-0.5.1.dist-info/licenses/LICENSE
sagemaker_jupyterlab_extension-0.5.1.dist-info/METADATA
sagemaker_jupyterlab_extension-0.5.1.dist-info/WHEEL
sagemaker_jupyterlab_extension-0.5.1.dist-info/top_level.txt
sagemaker_jupyterlab_extension-0.5.1.dist-info/RECORD
