Metadata-Version: 2.4
Name: sagemaker-jupyterlab-extension
Version: 0.5.1
Summary: SageMaker JupyterLab workspace primary extension module
Home-page: https://aws.amazon.com/sagemaker/
Author: Amazon
License: Amazon Software License
Keywords: Jupyter,JupyterLab,JupyterLab4
Platform: Linux
Platform: Mac OS X
Platform: Windows
Classifier: Programming Language :: Python
Classifier: Programming Language :: Python :: 3
Classifier: Programming Language :: Python :: 3.9
Classifier: Framework :: Jupyter
Requires-Python: >=3.9
License-File: LICENSE
Requires-Dist: jupyterlab>=4
Requires-Dist: jupyter-events>=0.6.0
Requires-Dist: sagemaker_jupyterlab_extension_common
Requires-Dist: jupyterlab-git<1.0.0,>=0.51.1
Requires-Dist: async-lru
Requires-Dist: aws_embedded_metrics
Provides-Extra: dev
Requires-Dist: pytest>=6; extra == "dev"
Requires-Dist: pytest-cov; extra == "dev"
Requires-Dist: black; extra == "dev"
Requires-Dist: pytest_jupyter; extra == "dev"
Dynamic: author
Dynamic: classifier
Dynamic: description
Dynamic: description-content-type
Dynamic: home-page
Dynamic: keywords
Dynamic: license
Dynamic: license-file
Dynamic: platform
Dynamic: provides-extra
Dynamic: requires-dist
Dynamic: requires-python
Dynamic: summary
